{
  "lastmod": "2025-06-28T01:40:57.019999",
  "books": [
    {
      "title": "The Art of Agile Development: Pragmatic Guide to Agile Software Development",
      "author": "James Shore",
      "link": "https://www.goodreads.com/book/show/1654215.The_Art_of_Agile_Development",
      "pages": 438,
      "date_started": "2025-06-19",
      "date_read": null,
      "date_added": "2025-06-26"
    },
    {
      "title": "La montagna sei tu: Trasformare l'autosabotaggio in autocontrollo",
      "author": "Brianna Wiest",
      "link": "https://www.goodreads.com/book/show/89466198-la-montagna-sei-tu",
      "pages": 225,
      "date_started": null,
      "date_read": null,
      "date_added": "2025-06-01"
    }
  ]
}